function_timing_decorator/__init__.py
function_timing_decorator/timer.py
function_timing_decorator-0.1.2.dist-info/licenses/LICENSE
function_timing_decorator-0.1.2.dist-info/METADATA
function_timing_decorator-0.1.2.dist-info/WHEEL
function_timing_decorator-0.1.2.dist-info/top_level.txt
function_timing_decorator-0.1.2.dist-info/RECORD
