Metadata-Version: 2.4
Name: function-timing-decorator
Version: 0.1.2
Summary: A professional-grade Python decorator to measure function execution time
Author-email: Gurnoor Singh Saini <sainigurnoor511@gmail.com>
License: MIT
Project-URL: Homepage, https://github.com/Sainigurnoor511/function-timing-decorator
Project-URL: Repository, https://github.com/Sainigurnoor511/function-timing-decorator
Requires-Python: >=3.7
License-File: LICENSE
Requires-Dist: rich>=13.0.0
Dynamic: license-file
